CHANGES.rst
MANIFEST.in
README.rst
requirements.txt
setup.py
githooks/__init__.py
githooks/base_check.py
githooks/checks.py
githooks/commit_checks.py
githooks/commit_list_checks.py
githooks/config.py
githooks/file_checks.py
githooks/git.py
githooks/pre_receive.py
githooks/utils.py
githooks/configs/__init__.py
githooks/configs/default.py
githooks/tests/__init__.py
githooks/tests/sample_config/default.yml
githooks/tests/sample_config/development.yml
sc_githooks.egg-info/PKG-INFO
sc_githooks.egg-info/SOURCES.txt
sc_githooks.egg-info/dependency_links.txt
sc_githooks.egg-info/entry_points.txt
sc_githooks.egg-info/requires.txt
sc_githooks.egg-info/top_level.txt