Metadata-Version: 1.2
Name: sc-githooks
Version: 0.1.9
Summary: Git pre-receive hook to check commits
Home-page: https://github.com/Scott-Lau/sc-githooks
Author: Scott Lau
Author-email: exceedego@126.com
License: MIT
Keywords: git git-hook python pre-receive hook
Platform: POSIX
Classifier: Programming Language :: Python :: 3
Classifier: Programming Language :: Python :: 3.6
Classifier: Programming Language :: Python :: 3.7
Classifier: Programming Language :: Python :: 3.8
Classifier: Programming Language :: Python :: 3.9
Classifier: License :: OSI Approved :: MIT License
Classifier: Operating System :: OS Independent
Classifier: Topic :: Software Development
Classifier: Topic :: Utilities
Requires-Python: >=3.6
